[{"web_url":"https://www.nytimes.com/2017/08/06/business/economy/fintech-startups-financial-services.html","snippet":"The FinTech Innovation Lab, a New York business-backed program, has been working to help financial-services start-ups sell their services in New York.","print_page":"1","blog":{},"source":"The New York Times","multimedia":[{"type":"image","subtype":"xlarge","url":"images/2017/08/07/business/07DB-FINTECH1/07DB-FINTECH1-articleLarge.jpg","height":400,"width":600,"rank":0,"legacy":{"xlargewidth":600,"xlarge":"images/2017/08/07/business/07DB-FINTECH1/07DB-FINTECH1-articleLarge.jpg","xlargeheight":400}},{"type":"image","subtype":"wide","url":"images/2017/08/07/business/07DB-FINTECH1/07DB-FINTECH1-thumbWide.jpg","height":126,"width":190,"rank":0,"legacy":{"wide":"images/2017/08/07/business/07DB-FINTECH1/07DB-FINTECH1-thumbWide.jpg","widewidth":190,"wideheight":126}},{"type":"image","subtype":"thumbnail","url":"images/2017/08/07/business/07DB-FINTECH1/07DB-FINTECH1-thumbStandard.jpg","height":75,"width":75,"rank":0,"legacy":{"thumbnailheight":75,"thumbnail":"images/2017/08/07/business/07DB-FINTECH1/07DB-FINTECH1-thumbStandard.jpg","thumbnailwidth":75}}],"headline":{"main":"Countering West Coast Pull, by Helping Finance Start-Ups Sell in New York","print_headline":"Boost for Finance Start-Ups Where It Counts: Wall Street"},"keywords":[{"isMajor":"N","rank":1,"name":"subject","value":"Start-ups"},{"isMajor":"N","rank":2,"name":"glocations","value":"New York City"},{"isMajor":"N","rank":3,"name":"subject","value":"Banking and Financial Institutions"},{"isMajor":"N","rank":4,"name":"organizations","value":"FinTech Innovation Lab"},{"isMajor":"N","rank":5,"name":"subject","value":"Venture Capital"},{"isMajor":"N","rank":6,"name":"persons","value":"Kravis, Henry R"},{"isMajor":"N","rank":7,"name":"persons","value":"Wilson, Fred (1961- )"}],"pub_date":"2017-08-06T19:37:45+0000","document_type":"article","new_desk":"Business","section_name":"Economy","byline":{"original":"By RANDALL SMITH"},"type_of_material":"News","_id":"5987701e95d0e0246f1fe640","word_count":1428,"score":0.016463678,"uri":"nyt://article/3b254fbb-2116-59a2-9577-c216f3afd4d7"}]
