[{"web_url":"https://www.nytimes.com/2017/04/02/business/media/ads-short-films-shot-on-an-iphone.html","snippet":"Artists and brands are collaborating on advertisements that move away from mere product placement, a practice so common that the Tribeca Film Festival has an award for it.","print_page":"1","blog":{},"source":"The New York Times","multimedia":[{"type":"image","subtype":"thumbnail","url":"images/2017/04/03/business/03adco1/03adco1-thumbStandard.jpg","height":75,"width":75,"rank":0,"legacy":{"thumbnailheight":75,"thumbnail":"images/2017/04/03/business/03adco1/03adco1-thumbStandard.jpg","thumbnailwidth":75}},{"type":"image","subtype":"xlarge","url":"images/2017/04/03/business/03adco1/03adco1-articleLarge.jpg","height":250,"width":600,"rank":0,"legacy":{"xlargewidth":600,"xlarge":"images/2017/04/03/business/03adco1/03adco1-articleLarge.jpg","xlargeheight":250}},{"type":"image","subtype":"wide","url":"images/2017/04/03/business/03adco1/03adco1-thumbWide.jpg","height":126,"width":190,"rank":0,"legacy":{"wide":"images/2017/04/03/business/03adco1/03adco1-thumbWide.jpg","widewidth":190,"wideheight":126}}],"headline":{"main":"The Ad Feels a Bit Like Oscar Bait, but It’s Trying to Sell You an iPhone","kicker":"Advertising","print_headline":"Brands Trade the Hard Sell for Short Films"},"keywords":[{"isMajor":"N","rank":1,"name":"subject","value":"Tribeca Film Festival (NYC)"},{"isMajor":"N","rank":2,"name":"subject","value":"Advertising and Marketing"},{"isMajor":"N","rank":3,"name":"organizations","value":"Apple Inc"},{"isMajor":"N","rank":4,"name":"organizations","value":"Atlantic Monthly"},{"isMajor":"N","rank":5,"name":"organizations","value":"Droga5"},{"isMajor":"N","rank":6,"name":"organizations","value":"Kenzo"},{"isMajor":"N","rank":7,"name":"persons","value":"Brownstein, Carrie"}],"pub_date":"2017-04-02T18:25:52+0000","document_type":"article","new_desk":"Business","section_name":"Media","byline":{"original":"By SAPNA MAHESHWARI"},"type_of_material":"News","_id":"58e1423795d0e02489b94c19","word_count":958,"score":0.0025889676},{"web_url":"https://www.nytimes.com/2017/04/02/technology/dyson-british-consumer-electronics-company.html","snippet":"With an eye for both design and engineering, this British consumer electronics company is aiming for — and winning — the high end of the market.","print_page":"1","blog":{},"source":"The New York Times","multimedia":[],"headline":{"main":"Dyson Is the Apple of Appliances (and Just as Secretive)","print_headline":"How Dyson Keeps Winning"},"keywords":[{"isMajor":"N","rank":1,"name":"subject","value":"Home Appliances"},{"isMajor":"N","rank":2,"name":"organizations","value":"Dyson"},{"isMajor":"N","rank":3,"name":"subject","value":"Vacuum Cleaners"},{"isMajor":"N","rank":4,"name":"subject","value":"Robots and Robotics"},{"isMajor":"N","rank":5,"name":"subject","value":"Engineering and Engineers"}],"pub_date":"2017-04-02T22:48:25+0000","document_type":"article","new_desk":"Business","byline":{"original":"By MARK SCOTT"},"type_of_material":"News","_id":"58e17fc895d0e02489b94c7a","word_count":1459,"score":0.0016515859}]
