[{"web_url":"https://www.nytimes.com/2017/02/25/technology/farhads-and-brians-week-in-tech-ubers-very-bad-month.html","snippet":"The ride-sharing company lurches from scandal to scandal to scandal, and Apple is set to open a very round new office.","print_page":"0","blog":{},"source":"The New York Times","multimedia":[{"type":"image","subtype":"thumbnail","url":"images/2017/02/26/technology/26technewsletter-web/26technewsletter-web-thumbStandard.jpg","height":75,"width":75,"rank":0,"legacy":{"thumbnailheight":75,"thumbnail":"images/2017/02/26/technology/26technewsletter-web/26technewsletter-web-thumbStandard.jpg","thumbnailwidth":75}},{"type":"image","subtype":"xlarge","url":"images/2017/02/26/technology/26technewsletter-web/26technewsletter-web-articleLarge.jpg","height":400,"width":600,"rank":0,"legacy":{"xlargewidth":600,"xlarge":"images/2017/02/26/technology/26technewsletter-web/26technewsletter-web-articleLarge.jpg","xlargeheight":400}},{"type":"image","subtype":"wide","url":"images/2017/02/26/technology/26technewsletter-web/26technewsletter-web-thumbWide.jpg","height":126,"width":190,"rank":0,"legacy":{"wide":"images/2017/02/26/technology/26technewsletter-web/26technewsletter-web-thumbWide.jpg","widewidth":190,"wideheight":126}}],"headline":{"main":"Farhad’s and Brian’s Week in Tech: Uber’s Very Bad Month","kicker":"Bits","print_headline":"Farhad’s and Brian’s Week in Tech: Uber’s Very Bad Month"},"keywords":[{"isMajor":"N","rank":1,"name":"organizations","value":"Uber Technologies Inc"},{"isMajor":"N","rank":2,"name":"persons","value":"Kalanick, Travis"},{"isMajor":"N","rank":3,"name":"organizations","value":"Apple Inc"},{"isMajor":"N","rank":4,"name":"organizations","value":"Facebook Inc"},{"isMajor":"N","rank":5,"name":"organizations","value":"WhatsApp Inc"},{"isMajor":"N","rank":6,"name":"organizations","value":"Waymo"}],"pub_date":"2017-02-25T14:00:06+0000","document_type":"article","new_desk":"Business","byline":{"original":"By FARHAD MANJOO and BRIAN X. CHEN"},"type_of_material":"News","_id":"58b18df07c459f2525d1e7a9","word_count":1312,"score":0.0005727589},{"web_url":"https://www.nytimes.com/2017/02/25/business/dealbook/warren-buffett-annual-letter.html","snippet":"The billionaire investor’s optimistic tone contrasts with President Trump’s darker descriptions. Mr. Buffett also gave credit to “ambitious immigrants.”","print_page":"12","blog":{},"source":"The New York Times","multimedia":[{"type":"image","subtype":"thumbnail","url":"images/2017/02/26/business/26db-buffett1/26db-buffett1-thumbStandard.jpg","height":75,"width":75,"rank":0,"legacy":{"thumbnailheight":75,"thumbnail":"images/2017/02/26/business/26db-buffett1/26db-buffett1-thumbStandard.jpg","thumbnailwidth":75}},{"type":"image","subtype":"xlarge","url":"images/2017/02/26/business/26db-buffett1/26db-buffett1-articleLarge.jpg","height":400,"width":600,"rank":0,"legacy":{"xlargewidth":600,"xlarge":"images/2017/02/26/business/26db-buffett1/26db-buffett1-articleLarge.jpg","xlargeheight":400}},{"type":"image","subtype":"wide","url":"images/2017/02/26/business/26db-buffett1/26db-buffett1-thumbWide.jpg","height":126,"width":190,"rank":0,"legacy":{"wide":"images/2017/02/26/business/26db-buffett1/26db-buffett1-thumbWide.jpg","widewidth":190,"wideheight":126}}],"headline":{"main":"Warren Buffett, in Annual Letter, Offers Hymn to U.S. Economy","print_headline":"Buffett, in Annual Letter, Offers Hymn to U.S. Economy and Praises Immigrants"},"keywords":[{"isMajor":"N","rank":1,"name":"persons","value":"Buffett, Warren E"},{"isMajor":"N","rank":2,"name":"subject","value":"United States Economy"},{"isMajor":"N","rank":3,"name":"subject","value":"Standard & Poor's 500-Stock Index"},{"isMajor":"N","rank":4,"name":"subject","value":"Immigration and Emigration"},{"isMajor":"N","rank":5,"name":"subject","value":"United States Politics and Government"},{"isMajor":"N","rank":6,"name":"organizations","value":"BNSF Railway"},{"isMajor":"N","rank":7,"name":"organizations","value":"Berkshire Hathaway Inc"},{"isMajor":"N","rank":8,"name":"organizations","value":"Geico (Government Employees Insurance Co)"},{"isMajor":"N","rank":9,"name":"organizations","value":"Goldman Sachs Group Inc"},{"isMajor":"N","rank":10,"name":"organizations","value":"Salomon Brothers"},{"isMajor":"N","rank":11,"name":"persons","value":"Clinton, Hillary Rodham"},{"isMajor":"N","rank":12,"name":"persons","value":"Trump, Donald J"}],"pub_date":"2017-02-25T17:10:48+0000","document_type":"article","new_desk":"Business","section_name":"DealBook","byline":{"original":"By LANDON THOMAS Jr"},"type_of_material":"News","_id":"58b1baa07c459f2525d1e7ed","word_count":627,"score":0.00015761689}]
