[{"web_url":"https://www.nytimes.com/2017/10/18/technology/personaltech/heif-photo-file-format.html","snippet":"With the latest updates for its Macs and mobile devices, Apple has added support for new image and video formats while keeping things compatible.","blog":{},"source":"The New York Times","multimedia":[{"type":"image","subtype":"xlarge","url":"images/2017/10/19/technology/personaltech/19techtipwebART/19techtipwebART-articleLarge.jpg","height":476,"width":600,"rank":0,"legacy":{"xlargewidth":600,"xlarge":"images/2017/10/19/technology/personaltech/19techtipwebART/19techtipwebART-articleLarge.jpg","xlargeheight":476}},{"type":"image","subtype":"wide","url":"images/2017/10/19/technology/personaltech/19techtipwebART/19techtipwebART-thumbWide.jpg","height":126,"width":190,"rank":0,"legacy":{"wide":"images/2017/10/19/technology/personaltech/19techtipwebART/19techtipwebART-thumbWide.jpg","widewidth":190,"wideheight":126}},{"type":"image","subtype":"thumbnail","url":"images/2017/10/19/technology/personaltech/19techtipwebART/19techtipwebART-thumbStandard.jpg","height":75,"width":75,"rank":0,"legacy":{"thumbnailheight":75,"thumbnail":"images/2017/10/19/technology/personaltech/19techtipwebART/19techtipwebART-thumbStandard.jpg","thumbnailwidth":75}}],"headline":{"main":"Using New Space-Saving Photo Files","kicker":"Tech Tip","print_headline":"Using New Space-Saving Photo Files"},"keywords":[{"isMajor":"N","rank":1,"name":"subject","value":"iOS (Operating System)"},{"isMajor":"N","rank":2,"name":"subject","value":"Photography"},{"isMajor":"N","rank":3,"name":"subject","value":"iPhone"},{"isMajor":"N","rank":4,"name":"organizations","value":"Apple Inc"}],"pub_date":"2017-10-18T13:33:39+0000","document_type":"article","new_desk":"Business","section_name":"Personal Tech","byline":{"original":"By J. D. BIERSDORFER"},"type_of_material":"Question","_id":"59e7584b7c459f246b62f50f","word_count":420,"score":2.9220092,"uri":"nyt://article/3ef3f081-d51a-50e7-bd51-f77c746cd211"},{"web_url":"https://www.nytimes.com/2017/10/18/technology/frightful-five-start-ups.html","snippet":"In Silicon Valley, small companies used to unseat big ones. Now the clutches of the five biggest tech companies are hard to escape.","print_page":"1","blog":{},"source":"The New York Times","multimedia":[{"type":"image","subtype":"xlarge","url":"images/2017/10/19/business/19STATE/19STATE-articleLarge.gif","height":360,"width":600,"rank":0,"legacy":{"xlargewidth":600,"xlarge":"images/2017/10/19/business/19STATE/19STATE-articleLarge.gif","xlargeheight":360}},{"type":"image","subtype":"wide","url":"images/2017/10/19/business/19STATE/19STATE-thumbWide.gif","height":126,"width":190,"rank":0,"legacy":{"wide":"images/2017/10/19/business/19STATE/19STATE-thumbWide.gif","widewidth":190,"wideheight":126}},{"type":"image","subtype":"thumbnail","url":"images/2017/10/19/business/19STATE/19STATE-thumbStandard.gif","height":75,"width":75,"rank":0,"legacy":{"thumbnailheight":75,"thumbnail":"images/2017/10/19/business/19STATE/19STATE-thumbStandard.gif","thumbnailwidth":75}}],"headline":{"main":"How the Frightful Five Put Start-Ups in a Lose-Lose Situation","kicker":"State of the Art","print_headline":"A Frightful Stranglehold On Tech Start-Ups"},"keywords":[{"isMajor":"N","rank":1,"name":"subject","value":"Computers and the Internet"},{"isMajor":"N","rank":2,"name":"subject","value":"Start-ups"},{"isMajor":"N","rank":3,"name":"organizations","value":"Snap Inc"},{"isMajor":"N","rank":4,"name":"subject","value":"Social Media"},{"isMajor":"N","rank":5,"name":"subject","value":"Innovation"},{"isMajor":"N","rank":6,"name":"organizations","value":"Facebook Inc"},{"isMajor":"N","rank":7,"name":"organizations","value":"Google Inc"},{"isMajor":"N","rank":8,"name":"organizations","value":"Amazon.com Inc"},{"isMajor":"N","rank":9,"name":"organizations","value":"Apple Inc"},{"isMajor":"N","rank":10,"name":"organizations","value":"Microsoft Corp"},{"isMajor":"N","rank":11,"name":"organizations","value":"IAC/InterActiveCorp"}],"pub_date":"2017-10-18T09:00:24+0000","document_type":"article","new_desk":"Business","byline":{"original":"By FARHAD MANJOO"},"type_of_material":"News","_id":"59e718367c459f246b62f437","word_count":1427,"score":1.5318719,"uri":"nyt://article/ff61a4c7-6844-5f0d-b26f-7c52bc6d3131"}]
